katsdpsigproc/__init__.py
katsdpsigproc/abc.py
katsdpsigproc/accel.py
katsdpsigproc/cuda.py
katsdpsigproc/fft.py
katsdpsigproc/fill.mako
katsdpsigproc/fill.py
katsdpsigproc/hreduce.mako
katsdpsigproc/maskedsum.mako
katsdpsigproc/maskedsum.py
katsdpsigproc/opencl.py
katsdpsigproc/percentile.mako
katsdpsigproc/percentile.py
katsdpsigproc/port.mako
katsdpsigproc/py.typed
katsdpsigproc/pytest_plugin.py
katsdpsigproc/rank.mako
katsdpsigproc/reduce.py
katsdpsigproc/resource.py
katsdpsigproc/transpose.mako
katsdpsigproc/transpose.py
katsdpsigproc/transpose_base.mako
katsdpsigproc/tune.py
katsdpsigproc/wg_reduce.mako
katsdpsigproc/asyncio/__init__.py
katsdpsigproc/asyncio/resource.py
katsdpsigproc/rfi/__init__.py
katsdpsigproc/rfi/background_median_filter.mako
katsdpsigproc/rfi/device.py
katsdpsigproc/rfi/host.py
katsdpsigproc/rfi/madnz.mako
katsdpsigproc/rfi/madnz_t.mako
katsdpsigproc/rfi/threshold_simple.mako
katsdpsigproc/rfi/threshold_simple_t.mako
katsdpsigproc/rfi/threshold_sum.mako
katsdpsigproc/rfi/twodflag.py
katsdpsigproc/test/__init__.py
katsdpsigproc/test/test_accel.py
katsdpsigproc-1.10.0.dist-info/licenses/LICENSE
katsdpsigproc-1.10.0.dist-info/METADATA
katsdpsigproc-1.10.0.dist-info/WHEEL
katsdpsigproc-1.10.0.dist-info/top_level.txt
katsdpsigproc-1.10.0.dist-info/RECORD
