Metadata-Version: 2.4
Name: katsdpsigproc
Version: 1.10.0
Summary: Karoo Array Telescope accelerated signal processing tools
Home-page: https://katsdpsigproc.readthedocs.io/
Author: MeerKAT SDP team
Author-email: sdpdev+katsdpsigproc@sarao.ac.za
License: Modified BSD
Classifier: License :: OSI Approved :: BSD License
Classifier: Programming Language :: Python
Classifier: Programming Language :: Python :: 3
Requires-Python: >=3.8
License-File: LICENSE
Requires-Dist: appdirs
Requires-Dist: decorator
Requires-Dist: importlib-resources; python_version < "3.9"
Requires-Dist: mako
Requires-Dist: numba>=0.36.1
Requires-Dist: numpy>=1.10
Requires-Dist: pandas
Requires-Dist: scipy
Requires-Dist: typing_extensions
Provides-Extra: cuda
Requires-Dist: pycuda>=2015.1.3; extra == "cuda"
Provides-Extra: opencl
Requires-Dist: pyopencl>=2017.2.1; extra == "opencl"
Provides-Extra: doc
Requires-Dist: sphinx>=1.3; extra == "doc"
Requires-Dist: sphinxcontrib-tikz; extra == "doc"
Requires-Dist: sphinx-rtd-theme; extra == "doc"
Provides-Extra: test
Requires-Dist: graphviz; extra == "test"
Requires-Dist: pytest; extra == "test"
Requires-Dist: pytest-asyncio; extra == "test"
Dynamic: license-file
